MeizhouGongzuoSixiaoshi/README.md
MeizhouGongzuoSixiaoshi/__init__.py
MeizhouGongzuoSixiaoshi/__main__.py
MeizhouGongzuoSixiaoshi/file.epub
MeizhouGongzuoSixiaoshi/index.html
MeizhouGongzuoSixiaoshi/css/__init__.py
MeizhouGongzuoSixiaoshi/css/annotations.css
MeizhouGongzuoSixiaoshi/css/main.css
MeizhouGongzuoSixiaoshi/css/normalize.css
MeizhouGongzuoSixiaoshi/css/popup.css
MeizhouGongzuoSixiaoshi/font/__init__.py
MeizhouGongzuoSixiaoshi/font/fontello.eot
MeizhouGongzuoSixiaoshi/font/fontello.svg
MeizhouGongzuoSixiaoshi/font/fontello.ttf
MeizhouGongzuoSixiaoshi/font/fontello.woff
MeizhouGongzuoSixiaoshi/img/__init__.py
MeizhouGongzuoSixiaoshi/img/annotator-glyph-sprite.png
MeizhouGongzuoSixiaoshi/img/annotator-icon-sprite.png
MeizhouGongzuoSixiaoshi/img/apple-touch-icon.png
MeizhouGongzuoSixiaoshi/img/cancelfullscreen.png
MeizhouGongzuoSixiaoshi/img/close.png
MeizhouGongzuoSixiaoshi/img/fullscreen.png
MeizhouGongzuoSixiaoshi/img/loader.gif
MeizhouGongzuoSixiaoshi/img/menu-icon.png
MeizhouGongzuoSixiaoshi/img/save.png
MeizhouGongzuoSixiaoshi/img/saved.png
MeizhouGongzuoSixiaoshi/img/settings-s.png
MeizhouGongzuoSixiaoshi/img/settings.png
MeizhouGongzuoSixiaoshi/img/star.png
MeizhouGongzuoSixiaoshi/js/__init__.py
MeizhouGongzuoSixiaoshi/js/epub.js
MeizhouGongzuoSixiaoshi/js/epub.min.js
MeizhouGongzuoSixiaoshi/js/epub.min.map
MeizhouGongzuoSixiaoshi/js/hooks.min.js
MeizhouGongzuoSixiaoshi/js/hooks.min.map
MeizhouGongzuoSixiaoshi/js/reader.js
MeizhouGongzuoSixiaoshi/js/reader.js.map
MeizhouGongzuoSixiaoshi/js/reader.min.js
MeizhouGongzuoSixiaoshi/js/reader.min.map
MeizhouGongzuoSixiaoshi/js/hooks/__init__.py
MeizhouGongzuoSixiaoshi/js/hooks/extensions/__init__.py
MeizhouGongzuoSixiaoshi/js/hooks/extensions/highlight.js
MeizhouGongzuoSixiaoshi/js/libs/__init__.py
MeizhouGongzuoSixiaoshi/js/libs/jquery.min.js
MeizhouGongzuoSixiaoshi/js/libs/localforage.min.js
MeizhouGongzuoSixiaoshi/js/libs/screenfull.js
MeizhouGongzuoSixiaoshi/js/libs/screenfull.min.js
meizhou_gongzuo_sixiaoshi-2022.10.15.0.dist-info/METADATA
meizhou_gongzuo_sixiaoshi-2022.10.15.0.dist-info/WHEEL
meizhou_gongzuo_sixiaoshi-2022.10.15.0.dist-info/entry_points.txt
meizhou_gongzuo_sixiaoshi-2022.10.15.0.dist-info/top_level.txt
meizhou_gongzuo_sixiaoshi-2022.10.15.0.dist-info/RECORD
